odoo/addons/project_task_ancestor/README.rst
odoo/addons/project_task_ancestor/__init__.py
odoo/addons/project_task_ancestor/__manifest__.py
odoo/addons/project_task_ancestor/i18n/es.po
odoo/addons/project_task_ancestor/i18n/it.po
odoo/addons/project_task_ancestor/i18n/project_task_ancestor.pot
odoo/addons/project_task_ancestor/models/__init__.py
odoo/addons/project_task_ancestor/models/account_analytic_line.py
odoo/addons/project_task_ancestor/models/project_report.py
odoo/addons/project_task_ancestor/models/project_task.py
odoo/addons/project_task_ancestor/models/timesheets_analysis_report.py
odoo/addons/project_task_ancestor/readme/CONTRIBUTORS.md
odoo/addons/project_task_ancestor/readme/DESCRIPTION.md
odoo/addons/project_task_ancestor/readme/USAGE.md
odoo/addons/project_task_ancestor/static/description/icon.png
odoo/addons/project_task_ancestor/static/description/index.html
odoo/addons/project_task_ancestor/tests/__init__.py
odoo/addons/project_task_ancestor/tests/test_project_task_ancestor.py
odoo/addons/project_task_ancestor/views/hr_timesheet_views.xml
odoo/addons/project_task_ancestor/views/project_task_views.xml
odoo_addon_project_task_ancestor-18.0.1.0.1.2.dist-info/METADATA
odoo_addon_project_task_ancestor-18.0.1.0.1.2.dist-info/WHEEL
odoo_addon_project_task_ancestor-18.0.1.0.1.2.dist-info/top_level.txt
odoo_addon_project_task_ancestor-18.0.1.0.1.2.dist-info/RECORD
